mirror_source/__init__.py
mirror_source/__main__.py
mirror_source/log.py
mirror_source-0.0.9.dist-info/LICENSE
mirror_source-0.0.9.dist-info/WHEEL
mirror_source-0.0.9.dist-info/METADATA
mirror_source-0.0.9.dist-info/RECORD
