Metadata-Version: 2.1
Name: mirror-source
Version: 0.0.9
Summary: 快速设置国内镜像源,方便记不住源地址的小伙子
Home-page: https://github.com/hbh112233abc/mirror-source
License: MIT
Keywords: pip,mirror
Author: hbh112233abc
Author-email: hbh112233abc@163.com
Requires-Python: >=3.7,<3.13
Classifier: License :: OSI Approved :: MIT License
Classifier: Programming Language :: Python :: 3
Classifier: Programming Language :: Python :: 3.10
Classifier: Programming Language :: Python :: 3.7
Classifier: Programming Language :: Python :: 3.8
Classifier: Programming Language :: Python :: 3.9
Requires-Dist: colorama (>=0.4.6,<0.5.0)
Requires-Dist: toml (>=0.10.2,<0.11.0)
Project-URL: Documentation, https://github.com/hbh112233abc/mirror-source
Project-URL: Repository, https://github.com/hbh112233abc/mirror-source
